[
  {
  "title": "Blast 2026",
  "releaseDate": "2026-05-28",
  "uploadDate": "2026-07-10",
  "description": " ⭐ IMDb: 7/10  | 🎬 Hindi | 720p | WEB-DL",
  "size": "1.73 GB",
  "link": "https://mega.nz/file/CngUVJLS#xWY9_GMxGVCBTrj_EV4ZsHBjCJ1KN5P4ZmPtDjLDDHE"
},

{
  "title": "Drishyam 3",
  "releaseDate": "2026-05-21",
  "uploadDate": "2026-07-10",
  "description": " ⭐ IMDb: 6.7/10  | 🎬 Hindi Dubbed | 720p | WEB-DL | The Hindi version starring Ajay Devgn is slated for theatrical release on October 2, 2026.",
  "size": "1.73 GB",
  "link": "https://mega.nz/file/muhAHbAS#H6R8sx2IZsHjfw6i55iVqTYTOu8xm0Q3WJ84BI6rl2A"
}

]
